setup.cfg
setup.py
django_materialize_form.egg-info/PKG-INFO
django_materialize_form.egg-info/SOURCES.txt
django_materialize_form.egg-info/dependency_links.txt
django_materialize_form.egg-info/requires.txt
django_materialize_form.egg-info/top_level.txt
materializeform/__init__.py
materializeform/meta.py
materializeform/templates/materializeform/field.html
materializeform/templates/materializeform/form.html
materializeform/templates/materializeform/formset.html
materializeform/templatetags/__init__.py
materializeform/templatetags/materialize.py