Metadata-Version: 1.1
Name: django-materialize-form
Version: 0.1.1
Summary: Django Materialize Form
Home-page: http://github.com/rajivm1991/django-materialize-form
Author: Rajiv Subramanian M
Author-email: rajiv.m1991@gmail.com
License: MIT
Download-URL: https://github.com/rajivm1991/django-materialize-form/tarball/0.1.1
Keywords: materialize,django
Platform: UNKNOWN
Classifier: Programming Language :: Python
Classifier: Topic :: Software Development :: Libraries :: Python Modules
Classifier: Framework :: Django
Classifier: Environment :: Web Environment
Classifier: Programming Language :: Python :: 2
Classifier: Programming Language :: Python :: 2.7
Classifier: Programming Language :: Python :: 3
Classifier: Programming Language :: Python :: 3.3
Classifier: Programming Language :: Python :: 3.4
